webrtc_vad/__init__.py
webrtc_vad/effects.py
webrtc_vad/vad.py
webrtc_vad_py-0.1.0.dist-info/METADATA
webrtc_vad_py-0.1.0.dist-info/WHEEL
webrtc_vad_py-0.1.0.dist-info/RECORD
