Metadata-Version: 2.4
Name: webrtc-vad-py
Version: 0.1.0
Summary: webrtc-vad-py wrapper for trimming speech clips
Requires-Python: >=3.9
Requires-Dist: librosa>=0.11.0
Requires-Dist: numpy>=2.0.2
Requires-Dist: webrtcvad>=2.0.10
